{
  "aks-sharedunp-20666395-vmss000008": {
    "cpu": {
      "raw": {
        "Requests": "17485m",
        "Limits": "17850m"
      },
      "percent": {
        "Requests": "(27%)",
        "Limits": "(28%)"
      }
    },
    "memory": {
      "raw": {
        "Requests": "88397505Ki",
        "Limits": "89375425Ki"
      },
      "percent": {
        "Requests": "(35%)",
        "Limits": "(35%)"
      }
    },
    "pods": {
      "5803-7ae1e829bdcc4291b1ae103688f344a6-2146822932": {
        "cpu": {
          "raw": {
            "Requests": "0",
            "Limits": "0"
          },
          "percent": {
            "Requests": "(0%)",
            "Limits": "(0%)"
          }
        },
        "memory": {
          "raw": {
            "Requests": "0",
            "Limits": "0"
          },
          "percent": {
            "Requests": "(0%)",
            "Limits": "(0%)"
          }
        },
        "time": "13s"
      },
      "5803-7ae1e829bdcc4291b1ae103688f344a6-srddz": {
        "cpu": {
          "raw": {
            "Requests": "100m",
            "Limits": "100m"
          },
          "percent": {
            "Requests": "(0%)",
            "Limits": "(0%)"
          }
        },
        "memory": {
          "raw": {
            "Requests": "100Mi",
            "Limits": "100Mi"
          },
          "percent": {
            "Requests": "(0%)",
            "Limits": "(0%)"
          }
        },
        "time": "11s"
      },
      "continuous-image-puller-h7ltg": {
        "cpu": {
          "raw": {
            "Requests": "0",
            "Limits": "0"
          },
          "percent": {
            "Requests": "(0%)",
            "Limits": "(0%)"
          }
        },
        "memory": {
          "raw": {
            "Requests": "0",
            "Limits": "0"
          },
          "percent": {
            "Requests": "(0%)",
            "Limits": "(0%)"
          }
        },
        "time": "6d5h"
      },
      "jupyter-1601270749627002-2d35647eaf386043b2966c54822a6901b8-2d11b65c48-2d014b-2d11eb-2d9931-2dee1cff9124db": {
        "cpu": {
          "raw": {
            "Requests": "8",
            "Limits": "8"
          },
          "percent": {
            "Requests": "(12%)",
            "Limits": "(12%)"
          }
        },
        "memory": {
          "raw": {
            "Requests": "64G",
            "Limits": "64G"
          },
          "percent": {
            "Requests": "(24%)",
            "Limits": "(24%)"
          }
        },
        "time": "6h57m"
      },
      "jupyter-1601282172366592-2d32b2ebb3a172411984883b21672bbf45-2daa321c5e-2d0165-2d11eb-2d9931-2dee1cff9124db": {
        "cpu": {
          "raw": {
            "Requests": "1",
            "Limits": "1"
          },
          "percent": {
            "Requests": "(1%)",
            "Limits": "(1%)"
          }
        },
        "memory": {
          "raw": {
            "Requests": "2G",
            "Limits": "2G"
          },
          "percent": {
            "Requests": "(0%)",
            "Limits": "(0%)"
          }
        },
        "time": "3h47m"
      },
      "jupyter-1601290356004339-2d86b58777dd2a4082b7cd191eaf4fe42c-2db8061f34-2d0178-2d11eb-2d9931-2dee1cff9124db": {
        "cpu": {
          "raw": {
            "Requests": "1",
            "Limits": "1"
          },
          "percent": {
            "Requests": "(1%)",
            "Limits": "(1%)"
          }
        },
        "memory": {
          "raw": {
            "Requests": "2G",
            "Limits": "2G"
          },
          "percent": {
            "Requests": "(0%)",
            "Limits": "(0%)"
          }
        },
        "time": "91m"
      },
      "jupyter-1601291990318597-2d7ad4243ee45849fdbce9c03fd2ab60df-2d8626b272-2d017c-2d11eb-2d9931-2dee1cff9124db": {
        "cpu": {
          "raw": {
            "Requests": "2",
            "Limits": "2"
          },
          "percent": {
            "Requests": "(3%)",
            "Limits": "(3%)"
          }
        },
        "memory": {
          "raw": {
            "Requests": "4G",
            "Limits": "4G"
          },
          "percent": {
            "Requests": "(1%)",
            "Limits": "(1%)"
          }
        },
        "time": "63m"
      },
      "jupyter-1601294594679925-2d498a0b5abf6f4e308769dba1bb7a4cb9-2d9678afda-2d0182-2d11eb-2d9931-2dee1cff9124db": {
        "cpu": {
          "raw": {
            "Requests": "1",
            "Limits": "1"
          },
          "percent": {
            "Requests": "(1%)",
            "Limits": "(1%)"
          }
        },
        "memory": {
          "raw": {
            "Requests": "2G",
            "Limits": "2G"
          },
          "percent": {
            "Requests": "(0%)",
            "Limits": "(0%)"
          }
        },
        "time": "20m"
      },
      "jupyter-1601294985772977-2d7e1d77bd16d941079f7fccd78599d10f-2d7f94c26c-2d0183-2d11eb-2d9931-2dee1cff9124db": {
        "cpu": {
          "raw": {
            "Requests": "4",
            "Limits": "4"
          },
          "percent": {
            "Requests": "(6%)",
            "Limits": "(6%)"
          }
        },
        "memory": {
          "raw": {
            "Requests": "16G",
            "Limits": "16G"
          },
          "percent": {
            "Requests": "(6%)",
            "Limits": "(6%)"
          }
        },
        "time": "13m"
      }
    }
  }
}
