{
  "aks-sharedunp-20666395-vmss000013": {
    "cpu": {
      "raw": {
        "Requests": "3485m",
        "Limits": "3850m"
      },
      "percent": {
        "Requests": "(5%)",
        "Limits": "(6%)"
      }
    },
    "memory": {
      "raw": {
        "Requests": "5019045120",
        "Limits": "7344175Ki"
      },
      "percent": {
        "Requests": "(1%)",
        "Limits": "(2%)"
      }
    },
    "pods": {
      "4739-7e00f9eff503479bb97871589682043c-3160683045": {
        "cpu": {
          "raw": {
            "Requests": "0",
            "Limits": "0"
          },
          "percent": {
            "Requests": "(0%)",
            "Limits": "(0%)"
          }
        },
        "memory": {
          "raw": {
            "Requests": "0",
            "Limits": "0"
          },
          "percent": {
            "Requests": "(0%)",
            "Limits": "(0%)"
          }
        },
        "time": "32h"
      },
      "5803-6efcb6f251f4474ea1cd4d3a3188e124-1722920436": {
        "cpu": {
          "raw": {
            "Requests": "0",
            "Limits": "0"
          },
          "percent": {
            "Requests": "(0%)",
            "Limits": "(0%)"
          }
        },
        "memory": {
          "raw": {
            "Requests": "0",
            "Limits": "0"
          },
          "percent": {
            "Requests": "(0%)",
            "Limits": "(0%)"
          }
        },
        "time": "14s"
      },
      "5803-6efcb6f251f4474ea1cd4d3a3188e124-r28j2": {
        "cpu": {
          "raw": {
            "Requests": "100m",
            "Limits": "100m"
          },
          "percent": {
            "Requests": "(0%)",
            "Limits": "(0%)"
          }
        },
        "memory": {
          "raw": {
            "Requests": "100Mi",
            "Limits": "100Mi"
          },
          "percent": {
            "Requests": "(0%)",
            "Limits": "(0%)"
          }
        },
        "time": "12s"
      },
      "continuous-image-puller-twfh9": {
        "cpu": {
          "raw": {
            "Requests": "0",
            "Limits": "0"
          },
          "percent": {
            "Requests": "(0%)",
            "Limits": "(0%)"
          }
        },
        "memory": {
          "raw": {
            "Requests": "0",
            "Limits": "0"
          },
          "percent": {
            "Requests": "(0%)",
            "Limits": "(0%)"
          }
        },
        "time": "7d12h"
      },
      "up-pod-1cpu2gbram3-6-2r-7351d0b7-8b86-4d38-b21a-22ae425f9bfc": {
        "cpu": {
          "raw": {
            "Requests": "1",
            "Limits": "1"
          },
          "percent": {
            "Requests": "(1%)",
            "Limits": "(1%)"
          }
        },
        "memory": {
          "raw": {
            "Requests": "1500M",
            "Limits": "2G"
          },
          "percent": {
            "Requests": "(0%)",
            "Limits": "(0%)"
          }
        },
        "time": "154m"
      },
      "up-pod-1cpu2gbram3-6-2r-784e30f0-82e3-482e-ae5c-dfd862b1b08e": {
        "cpu": {
          "raw": {
            "Requests": "1",
            "Limits": "1"
          },
          "percent": {
            "Requests": "(1%)",
            "Limits": "(1%)"
          }
        },
        "memory": {
          "raw": {
            "Requests": "1500M",
            "Limits": "2G"
          },
          "percent": {
            "Requests": "(0%)",
            "Limits": "(0%)"
          }
        },
        "time": "5d8h"
      },
      "up-pod-1cpu2gbram3-6-2r-fc06fb20-0c93-439d-b0e3-7c558b0bad25": {
        "cpu": {
          "raw": {
            "Requests": "1",
            "Limits": "1"
          },
          "percent": {
            "Requests": "(1%)",
            "Limits": "(1%)"
          }
        },
        "memory": {
          "raw": {
            "Requests": "1500M",
            "Limits": "2G"
          },
          "percent": {
            "Requests": "(0%)",
            "Limits": "(0%)"
          }
        },
        "time": "39m"
      }
    }
  }
}
